{
    "APPLICATION_THEME": "default",
    "accountCloudGuid": "047da162-d5b8-4088-af89-0f280b71528e",
    "appaddrkey": "",
    "appidkey": "FileGallery",
    "appmenu": {
        "context": {
            "channel": "mobile",
            "platform": "iphone"
        },
        "desktop": {
            "data": [
                {
                    "icon": {
                        "default": "option1.png"
                    },
                    "id": "appmenuitemid1",
                    "kuid": "a22e1448a73149b681bd50cb23abcce3",
                    "title": "Item 1"
                },
                {
                    "icon": {
                        "default": "option2.png"
                    },
                    "id": "appmenuitemid2",
                    "kuid": "h34f06b90759469e8a1466cc45155d8f",
                    "title": "Item 2"
                },
                {
                    "icon": {
                        "default": "option3.png"
                    },
                    "id": "appmenuitemid3",
                    "kuid": "c9cfecc6e33344fdbdc7dbed3dcc22ba",
                    "title": "Item 3"
                },
                {
                    "icon": {
                        "default": "option4.png"
                    },
                    "id": "appmenuitemid4",
                    "kuid": "d620122d8b214e91b8af215968b5edd8",
                    "title": "Item 4"
                }
            ]
        },
        "focusSkin": null,
        "focusskin": null,
        "mobile": {
            "data": [
                {
                    "android": {
                        "showAsFlag": 0
                    },
                    "icon": {
                        "default": "option1.png"
                    },
                    "id": "appmenuitemid1",
                    "kuid": "e5f4811a08804dccaf658be4c53fda77",
                    "title": "Item 1"
                },
                {
                    "android": {
                        "showAsFlag": 0
                    },
                    "icon": {
                        "default": "option2.png"
                    },
                    "id": "appmenuitemid2",
                    "kuid": "cefb8077e91049bf9608467045ce5929",
                    "title": "Item 2"
                },
                {
                    "android": {
                        "showAsFlag": 0
                    },
                    "icon": {
                        "default": "option3.png"
                    },
                    "id": "appmenuitemid3",
                    "kuid": "e0f67355bfca49c489aee2d824e980a9",
                    "title": "Item 3"
                },
                {
                    "android": {
                        "showAsFlag": 0
                    },
                    "icon": {
                        "default": "option4.png"
                    },
                    "id": "appmenuitemid4",
                    "kuid": "ia7a2e2e6cce42bfa686b4c95c2ebb1e",
                    "title": "Item 4"
                }
            ]
        },
        "osPlatform": "",
        "osVersion": "iOS7",
        "skin": null,
        "tablet": {
            "data": [
                {
                    "android": {
                        "showAsFlag": 0
                    },
                    "icon": {
                        "default": "option1.png"
                    },
                    "id": "appmenuitemid1",
                    "kuid": "bbe4b01b7baf4d268d784752562e273e",
                    "title": "Item 1",
                    "windows8": {
                        "appBarButtonStyle": "No Style",
                        "position": "BOTTOM_LEFT"
                    }
                },
                {
                    "android": {
                        "showAsFlag": 0
                    },
                    "icon": {
                        "default": "option2.png"
                    },
                    "id": "appmenuitemid2",
                    "kuid": "ddf667d2bd0a4b999567f8b809094bb6",
                    "title": "Item 2",
                    "windows8": {
                        "appBarButtonStyle": "No Style",
                        "position": "BOTTOM_LEFT"
                    }
                },
                {
                    "android": {
                        "showAsFlag": 0
                    },
                    "icon": {
                        "default": "option3.png"
                    },
                    "id": "appmenuitemid3",
                    "kuid": "g06fcb32a95d44e6bcc09f847a9d80fd",
                    "title": "Item 3",
                    "windows8": {
                        "appBarButtonStyle": "No Style",
                        "position": "BOTTOM_LEFT"
                    }
                },
                {
                    "android": {
                        "showAsFlag": 0
                    },
                    "icon": {
                        "default": "option4.png"
                    },
                    "id": "appmenuitemid4",
                    "kuid": "ica981b0354a417e88deb1b13342642f",
                    "title": "Item 4",
                    "windows8": {
                        "appBarButtonStyle": "No Style",
                        "position": "BOTTOM_LEFT"
                    }
                }
            ]
        },
        "wType": "Appmenu"
    },
    "appnamekey": "Gallery",
    "apppackagekey": "",
    "appversionkey": "1.0.0",
    "build": "debug",
    "category": "app",
    "cordovaModified": false,
    "cordovaVersionInfo": {
        "useGlobalCordova": false
    },
    "createdVizVersion": "8.0.0",
    "createdgaversion": "8.0.0",
    "currentgaversion": "8.1.4",
    "defaultlocalekey": "en_US",
    "defaulttheme": "defaultTheme",
    "desktopstartupformkey": "",
    "desktopwebbasefontsize": "12",
    "enableCordova": false,
    "enableCustomData": false,
    "enableIdForAutomation": false,
    "enableactionbar": false,
    "ide_appEvents": {
        "mobile": {
            "appservice": "AS_AppEvents_de757c55a11441119168673966544f8d",
            "postappinit": "AS_AppEvents_b72cee78ea0842748f56e52da33b6e5c"
        }
    },
    "isA11yConfigEnabled": true,
    "isDpScaleFactor": true,
    "isMVC": true,
    "isNewAppWithRespectToAndroidPackageName": "",
    "konyVizVersion": "8.1.4",
    "mastersProperties": {
        "mastersVersion": "2.0.0"
    },
    "mwaddrkey": "",
    "mwhttpsportkey": "",
    "mwportkey": "",
    "nativeContainerProperties": {
        "isModified": true,
        "isEnableJSContainer": true,
        "isEnableJSContainerAndroid": true,
        "isEnableJSContaineriOS": true
    },
    "project.type": "js",
    "projectCloudGuid": "9bde1f77-c15f-485d-bd70-2980716a496d",
    "project_version": "sprint30",
    "prototype": {
        "PublishMode": "public",
        "createdBy": "Shradhey Tripathi",
        "createdById": "c20f2db7-72db-43c5-a026-c765f9a72511",
        "createdOn": "2017-09-21T06:32:31.833Z",
        "resourceId": "4f859404-5634-42ac-80d6-84923301a995",
        "shareGuid": "61VZT"
    },
    "referenceWidth": "375",
    "startupformkey": "a06dee32a025472db9e707478103e8a7",
    "statusBarHidden": "false",
    "vendornamekey": "KonyLabs",
    "wap_android240_fontsize": "12",
    "wap_android320_fontsize": "12",
    "wap_android360_fontsize": "12",
    "wap_android400_fontsize": "12",
    "wap_android440_fontsize": "12",
    "wap_android480_fontsize": "12",
    "wap_android640_fontsize": "12",
    "wap_bb240_fontsize": "12",
    "wap_bb320_fontsize": "12",
    "wap_bb360_fontsize": "12",
    "wap_bb400_fontsize": "12",
    "wap_bb440_fontsize": "12",
    "wap_bb480_fontsize": "12",
    "wap_ip_fontsize": "12",
    "wap_spaandroidtab_fontsize": "12",
    "wap_spaandroidtabhdpi_fontsize": "12",
    "wap_spaandroidtabldpi_fontsize": "12",
    "wap_spaandroidtabmdpi_fontsize": "12",
    "wap_spaipad_fontsize": "12",
    "wap_spawindowstab_fontsize": "12",
    "wap_winphone320_fontsize": "12",
    "wap_winphone480_fontsize": "12",
    "watchos_companionSettings2x29": "",
    "watchos_companionSettings3x29": "",
    "watchos_homeScreen40": "",
    "watchos_longlooknotificationicon_42": "",
    "watchos_notificationcentericon_38": "",
    "watchos_notificationcentericon_42": "",
    "watchos_shortlooknotificationicon_38": "",
    "watchos_shortlooknotificationicon_42": "",
    "watchos_watchMarketing1x": "",
    "winmobileguidkey": ""
}